CHANGELOG.md
LICENSE
README.md
narq/__init__.py
narq/cli.py
narq/constants.py
narq/enums.py
narq/exceptions.py
narq/server/__init__.py
narq/server/app.py
narq/server/depends.py
narq/server/models.py
narq/server/responses.py
narq/server/routes/__init__.py
narq/server/routes/index.py
narq/server/routes/job.py
narq/server/routes/result.py
narq/server/routes/task.py
narq/server/routes/worker.py
narq/server/schemas.py
narq/server/static/favicon.svg
narq/server/static/index.css
narq/server/templates/base.html
narq/server/templates/dashboard.html
narq/server/templates/job.html
narq/server/templates/result.html
narq/server/templates/task.html
narq/server/templates/widgets/formatters.html
narq/server/templates/widgets/task_actions.html
narq/server/templates/worker.html
narq/signals.py
narq/task.py
narq/utils.py
narq/version.py
narq/worker.py
narq-0.2.1.dist-info/LICENSE
narq-0.2.1.dist-info/METADATA
narq-0.2.1.dist-info/WHEEL
narq-0.2.1.dist-info/entry_points.txt
narq-0.2.1.dist-info/RECORD
