Metadata-Version: 2.1
Name: narq
Version: 0.2.1
Summary: A distributed task queue built with asyncio and redis, with built-in web interface
Home-page: https://github.com/kita99/narq.git
License: Apache-2.0
Keywords: asyncio,task,arq,queue,distributed
Author: Adrian
Author-email: adriandinis99@gmail.com
Requires-Python: >=3.8
Classifier: License :: OSI Approved :: Apache Software License
Classifier: Programming Language :: Python :: 3
Classifier: Programming Language :: Python :: 3.8
Classifier: Programming Language :: Python :: 3.9
Classifier: Programming Language :: Python :: 3.10
Classifier: Programming Language :: Python :: 3.11
Classifier: Programming Language :: Python :: 3.12
Provides-Extra: mysql
Provides-Extra: postgres
Requires-Dist: aiofiles
Requires-Dist: async-timeout (>=4.0.3,<5.0.0)
Requires-Dist: asyncmy (>=0.2.8,<0.3.0) ; extra == "mysql"
Requires-Dist: asyncpg ; extra == "postgres"
Requires-Dist: click
Requires-Dist: crontab
Requires-Dist: fastapi[all]
Requires-Dist: loguru
Requires-Dist: redis (>=5.0.1,<6.0.0)
Requires-Dist: tortoise-orm (>=0.20.0,<0.21.0)
Project-URL: Documentation, https://github.com/kita99/narq/blob/master/README.md
Project-URL: Repository, https://github.com/kita99/narq.git
